spider_py/__init__.py
spider_py/client/__init__.py
spider_py/client/data.py
spider_py/client/driver.py
spider_py/client/job.py
spider_py/client/task.py
spider_py/client/task_context.py
spider_py/client/task_graph.py
spider_py/core/__init__.py
spider_py/core/data.py
spider_py/core/driver.py
spider_py/core/job.py
spider_py/core/task.py
spider_py/core/task_graph.py
spider_py/storage/__init__.py
spider_py/storage/jdbc_url.py
spider_py/storage/job_utils.py
spider_py/storage/mariadb_storage.py
spider_py/storage/storage.py
spider_py/task_executor/__init__.py
spider_py/task_executor/task_executor.py
spider_py/task_executor/task_executor_message.py
spider_py/type/__init__.py
spider_py/type/tdl_convert.py
spider_py/type/tdl_parse.py
spider_py/type/tdl_type.py
spider_py/type/type.py
spider_py/type/utils.py
spider_py/utils/__init__.py
spider_py/utils/serde.py
yscope_spider_py-0.2.1.dist-info/METADATA
yscope_spider_py-0.2.1.dist-info/WHEEL
yscope_spider_py-0.2.1.dist-info/entry_points.txt
yscope_spider_py-0.2.1.dist-info/licenses/LICENSE
yscope_spider_py-0.2.1.dist-info/RECORD
