Metadata-Version: 2.4
Name: yscope-spider-py
Version: 0.2.1
Summary: A distributed task execution framework.
Author-email: Sitao Wang <sitao.wang@yscope.com>, Zhihao Lin <lin.zhihao@yscope.com>
License-Expression: Apache-2.0
License-File: LICENSE
Classifier: License :: OSI Approved :: Apache Software License
Classifier: Typing :: Typed
Requires-Python: >=3.10
Requires-Dist: lark>=1.2.2
Requires-Dist: mariadb>=1.1.14
Requires-Dist: msgpack-types>=0.5.0
Requires-Dist: msgpack<1.2.0,>=1.1.0
